{
  "COMPANY_ADDRESS": {
    "description": "Primary business address of the organization",
    "default_value": "[COMPANY ADDRESS]",
    "category": "contact",
    "added_date": "2025-09-22T18:45:00.000000",
    "source_manual": "common_variables"
  },
  "COMPANY_PHONE": {
    "description": "Main phone number for the organization",
    "default_value": "[PHONE NUMBER]",
    "category": "contact",
    "added_date": "2025-09-22T18:45:00.000000",
    "source_manual": "common_variables"
  },
  "COMPANY_EMAIL": {
    "description": "General contact email address",
    "default_value": "[EMAIL ADDRESS]",
    "category": "contact",
    "added_date": "2025-09-22T18:45:00.000000",
    "source_manual": "common_variables"
  },
  "COMPANY_WEBSITE": {
    "description": "Organization's website URL",
    "default_value": "[WEBSITE URL]",
    "category": "contact",
    "added_date": "2025-09-22T18:45:00.000000",
    "source_manual": "common_variables"
  },
  "JURISDICTION": {
    "description": "Legal jurisdiction governing this policy",
    "default_value": "[JURISDICTION]",
    "category": "legal",
    "added_date": "2025-09-22T18:45:00.000000",
    "source_manual": "common_variables"
  },
  "BUSINESS_HOURS": {
    "description": "Standard operating hours for the organization",
    "default_value": "[BUSINESS HOURS]",
    "category": "operations",
    "added_date": "2025-09-22T18:45:00.000000",
    "source_manual": "common_variables"
  },
  "EMERGENCY_CONTACT": {
    "description": "Emergency contact information or number",
    "default_value": "[EMERGENCY CONTACT]",
    "category": "contact",
    "added_date": "2025-09-22T18:45:00.000000",
    "source_manual": "common_variables"
  },
  "DOCUMENT_CLASSIFICATION": {
    "description": "Security classification of this document",
    "default_value": "Internal Use",
    "category": "security",
    "added_date": "2025-09-22T18:45:00.000000",
    "source_manual": "common_variables"
  },
  "SCOPE_EMPLOYEES": {
    "description": "Employee groups covered by this policy",
    "default_value": "All employees, contractors, and temporary staff",
    "category": "scope",
    "added_date": "2025-09-22T18:45:00.000000",
    "source_manual": "common_variables"
  },
  "FISCAL_YEAR": {
    "description": "Organization's fiscal year period",
    "default_value": "[FISCAL YEAR]",
    "category": "dates",
    "added_date": "2025-09-22T18:45:00.000000",
    "source_manual": "common_variables"
  }
}